{
  "updated_iso": "2025-10-02T16:42:37.442402+00:00",
  "count": 1,
  "items": [
    {
      "id": "https-therams-com-news-rams-mister-cartoon-la-bold-collection-celebrating-los-angeles-culture",
      "title": "Los Angeles Rams and legendary artist Mister Cartoon drop \"LA Bold\" Collection celebrating Los Angeles culture",
      "link": "https://therams.com/news/rams-mister-cartoon-la-bold-collection-celebrating-los-angeles-culture",
      "source": "Los Angeles Rams (Official)",
      "ts": 1759397160.0,
      "published_iso": "2025-10-02T09:26:00+00:00"
    }
  ]
}