{
  "updated_iso": "2026-05-02T22:03:04.442749+00:00",
  "count": 3,
  "items": [
    {
      "id": "https-sports-yahoo-com-articles-rams-insider-expects-50-50-210312267-html",
      "title": "Rams insider expects 50-50 split for Kyren Williams, Blake Corum",
      "link": "https://sports.yahoo.com/articles/rams-insider-expects-50-50-210312267.html",
      "source": "Yahoo Sports",
      "ts": 1777731000.0,
      "published_iso": "2026-05-02T14:10:00+00:00"
    },
    {
      "id": "https-si-com-nfl-rams-onsi-los-angeles-mock-draft-grabbing-as-many-game-changers-as-possible",
      "title": "Rams Mock Draft: Grabbing As Many Game-Changers As Possible",
      "link": "https://si.com/nfl/rams/onsi/los-angeles-mock-draft-grabbing-as-many-game-changers-as-possible",
      "source": "Sports Illustrated",
      "ts": 1774198800.0,
      "published_iso": "2026-03-22T17:00:00+00:00"
    },
    {
      "id": "https-bleacherreport-com-los-angeles-rams",
      "title": "Los Angeles Rams",
      "link": "https://bleacherreport.com/los-angeles-rams",
      "source": "Bleacher Report",
      "ts": 1747293300.0,
      "published_iso": "2025-05-15T07:15:00+00:00"
    }
  ]
}