{
  "updated_iso": "2026-03-13T20:19:35.382771+00:00",
  "count": 1,
  "items": [
    {
      "id": "https-sports-yahoo-com-articles-why-blockbuster-trent-mcduffie-trade-191151789-html",
      "title": "Why blockbuster Trent McDuffie trade and $124M extension is 'smart' move for Rams",
      "link": "https://sports.yahoo.com/articles/why-blockbuster-trent-mcduffie-trade-191151789.html",
      "source": "Yahoo Sports",
      "ts": 1773405900.0,
      "published_iso": "2026-03-13T12:45:00+00:00"
    }
  ]
}