{
  "updated_iso": "2026-07-03T21:36:08.350257+00:00",
  "count": 2,
  "items": [
    {
      "id": "https-sports-yahoo-com-articles-rams-could-trade-solution-lions-170726500-html",
      "title": "Rams Could Have Trade Solution for Lions at Cornerback Following Terrion Arnold Release",
      "link": "https://sports.yahoo.com/articles/rams-could-trade-solution-lions-170726500.html",
      "source": "Yahoo Sports",
      "ts": 1783089180.0,
      "published_iso": "2026-07-03T14:33:00+00:00"
    },
    {
      "id": "https-sports-yahoo-com-articles-rams-dl-kobie-turner-no-160257799-html",
      "title": "Rams DL Kobie Turner: No. 6 Player Looks Ready to Become Established Star",
      "link": "https://sports.yahoo.com/articles/rams-dl-kobie-turner-no-160257799.html",
      "source": "Yahoo Sports",
      "ts": 1783084440.0,
      "published_iso": "2026-07-03T13:14:00+00:00"
    }
  ]
}